odoo/addons/ssi_project_autocreate_analytic_account/README.rst
odoo/addons/ssi_project_autocreate_analytic_account/__init__.py
odoo/addons/ssi_project_autocreate_analytic_account/__manifest__.py
odoo/addons/ssi_project_autocreate_analytic_account/models/__init__.py
odoo/addons/ssi_project_autocreate_analytic_account/models/project_project.py
odoo/addons/ssi_project_autocreate_analytic_account/models/project_type.py
odoo/addons/ssi_project_autocreate_analytic_account/static/description/icon.png
odoo/addons/ssi_project_autocreate_analytic_account/views/project_project_views.xml
odoo/addons/ssi_project_autocreate_analytic_account/views/project_type_views.xml
odoo14_addon_ssi_project_autocreate_analytic_account-14.0.1.1.0.dist-info/METADATA
odoo14_addon_ssi_project_autocreate_analytic_account-14.0.1.1.0.dist-info/WHEEL
odoo14_addon_ssi_project_autocreate_analytic_account-14.0.1.1.0.dist-info/top_level.txt
odoo14_addon_ssi_project_autocreate_analytic_account-14.0.1.1.0.dist-info/RECORD
